{
  "trace_samples": [
    {
      "banned_keys": [],
      "entity_slots_keys": [
        "what",
        "when",
        "where",
        "who"
      ],
      "group_id": 0,
      "has_pointer": true,
      "pointer": {
        "doc": "group-0-dda0d9ca",
        "end": 46,
        "start": 0
      },
      "trace_id": "group-0-dda0d9ca:0"
    },
    {
      "banned_keys": [],
      "entity_slots_keys": [
        "what",
        "when",
        "where",
        "who"
      ],
      "group_id": 1,
      "has_pointer": true,
      "pointer": {
        "doc": "group-1-e3c583b0",
        "end": 54,
        "start": 0
      },
      "trace_id": "group-1-e3c583b0:1"
    },
    {
      "banned_keys": [],
      "entity_slots_keys": [
        "what",
        "when",
        "where",
        "who"
      ],
      "group_id": 2,
      "has_pointer": true,
      "pointer": {
        "doc": "group-2-d2d80d72",
        "end": 49,
        "start": 0
      },
      "trace_id": "group-2-d2d80d72:2"
    },
    {
      "banned_keys": [],
      "entity_slots_keys": [
        "what",
        "when",
        "where",
        "who"
      ],
      "group_id": 3,
      "has_pointer": true,
      "pointer": {
        "doc": "group-3-e44d5830",
        "end": 47,
        "start": 0
      },
      "trace_id": "group-3-e44d5830:3"
    },
    {
      "banned_keys": [],
      "entity_slots_keys": [
        "what",
        "when",
        "where",
        "who"
      ],
      "group_id": 4,
      "has_pointer": true,
      "pointer": {
        "doc": "group-4-4af5a9fd",
        "end": 46,
        "start": 0
      },
      "trace_id": "group-4-4af5a9fd:4"
    }
  ]
}